{
  "sections": {
    "image_banner_jVfcNT": {
      "type": "image-banner",
      "blocks": {
        "heading_PitMXX": {
          "type": "heading",
          "settings": {
            "heading": "Find Our Bikins On Madam Sissi",
            "heading_size": "h1"
          }
        },
        "buttons_Ajde6G": {
          "type": "buttons",
          "settings": {
            "button_label_1": "New Arrivals",
            "button_link_1": "shopify:\/\/collections",
            "button_style_secondary_1": false,
            "button_label_2": "On Sale",
            "button_link_2": "shopify:\/\/collections",
            "button_icon": "sale-tag",
            "button_style_secondary_2": true
          }
        }
      },
      "block_order": [
        "heading_PitMXX",
        "buttons_Ajde6G"
      ],
      "settings": {
        "image": "shopify:\/\/shop_images\/Screenshot_2024-07-23_at_11.37.12_AM.png",
        "image_position": "top center",
        "image_overlay_opacity": 0,
        "image_height": "medium",
        "desktop_content_position": "middle-center",
        "show_text_box": true,
        "desktop_content_alignment": "center",
        "color_scheme": "scheme-1",
        "image_behavior": "none",
        "mobile_image": "shopify:\/\/shop_images\/Screenshot_2024-07-23_at_12.48.40_PM.png",
        "mobile_content_position": "bottom-center",
        "mobile_content_alignment": "center",
        "stack_images_on_mobile": false,
        "show_text_below": false
      }
    },
    "svg_text_column_8a7bL6": {
      "type": "svg-text-column",
      "blocks": {
        "svg_text_h9KXnd": {
          "type": "svg_text",
          "settings": {
            "svg_file_icon": "box",
            "description": "Entraga Gratuita a Partir de $50"
          }
        },
        "svg_text_br4frU": {
          "type": "svg_text",
          "settings": {
            "svg_file_icon": "secure",
            "description": "Entraga Gratuita a Partir de $50"
          }
        },
        "svg_text_C8ECK9": {
          "type": "svg_text",
          "settings": {
            "svg_file_icon": "back",
            "description": "Devolución Disponible"
          }
        }
      },
      "block_order": [
        "svg_text_h9KXnd",
        "svg_text_br4frU",
        "svg_text_C8ECK9"
      ],
      "settings": {
      }
    },
    "shape_carousel_collections_KVVNwB": {
      "type": "shape-carousel-collections",
      "settings": {
        "shape_collection_header": "",
        "collections_links": "diamond-navigation"
      }
    },
    "product_carousel_rmipzA": {
      "type": "product-carousel",
      "settings": {
        "section_header_text": "New Arrivals",
        "collection": "swimwear"
      }
    },
    "wide_banner_rKTG8i": {
      "type": "wide-banner",
      "settings": {
        "image": "shopify:\/\/shop_images\/Group_98.png",
        "title": "Titulo de Banner Aqui",
        "content": "Lorem ipsum dolor sit amet consectetur. Metus amet non faucibus odio lacinia nam.",
        "button_label": "Ver Cosméticos",
        "link": "shopify:\/\/products\/animal-print-two-pieces-hibikini",
        "background_pattern": "light",
        "blur_color": "#ffffff"
      }
    },
    "collections_navigation_preview_J9bqUd": {
      "type": "collections-navigation-preview",
      "blocks": {
        "collection_XAQWhr": {
          "type": "collection",
          "settings": {
            "collection": "hibikini",
            "collection_title": "Hibikini",
            "collection_description": "Collection description for Hibikini",
            "collection_image": "shopify:\/\/shop_images\/Screenshot2024-07-31at12.01.20PM.png"
          }
        },
        "collection_RqQYDK": {
          "type": "collection",
          "settings": {
            "collection": "aulala",
            "collection_title": "Aulala Collection",
            "collection_description": "This is the description for Aulala",
            "collection_image": "shopify:\/\/shop_images\/Screenshot2024-07-28at8.59.54AM.png"
          }
        },
        "collection_M8Grh9": {
          "type": "collection",
          "settings": {
            "collection": "vidoya",
            "collection_title": "Vidoya",
            "collection_description": "Collection description for Vidoya",
            "collection_image": "shopify:\/\/shop_images\/Screenshot2024-07-26at10.38.22AM.png"
          }
        },
        "collection_g3CYRx": {
          "type": "collection",
          "settings": {
            "collection": "one-piece",
            "collection_title": "One Piece",
            "collection_description": "Collection description for One Piece",
            "collection_image": "shopify:\/\/shop_images\/Screenshot2024-07-28at9.03.59AM.png"
          }
        }
      },
      "block_order": [
        "collection_XAQWhr",
        "collection_RqQYDK",
        "collection_M8Grh9",
        "collection_g3CYRx"
      ],
      "settings": {
        "collection_navigation_header": ""
      }
    },
    "collection_carousel_rnKXtp": {
      "type": "collection-carousel",
      "blocks": {
        "collection_wjpBrz": {
          "type": "collection",
          "settings": {
            "collection": "hibikini"
          }
        },
        "collection_8ajqKD": {
          "type": "collection",
          "settings": {
            "collection": "trikinis"
          }
        },
        "collection_a8p4nA": {
          "type": "collection",
          "settings": {
            "collection": "one-piece"
          }
        }
      },
      "block_order": [
        "collection_wjpBrz",
        "collection_8ajqKD",
        "collection_a8p4nA"
      ],
      "settings": {
        "title": "Colleciones Destacadas"
      }
    },
    "map_store_location_jem9Qa": {
      "type": "map-store-location",
      "blocks": {
        "address_immgDx": {
          "type": "address",
          "settings": {
            "address": "1600 Amphitheatre Parkway, Mountain View, CA 94043, United States"
          }
        },
        "schedule_rH7Acx": {
          "type": "schedule",
          "settings": {
            "schedule": "Lunes a Viernes de 9:00 a 18:00"
          }
        }
      },
      "block_order": [
        "address_immgDx",
        "schedule_rH7Acx"
      ],
      "settings": {
        "title": "VISITANOS EN NUESTRA TIENDA",
        "sub_title": "Si estas de visita en madeira, ven y conoce nuestra tienda física",
        "map_iframe": "<iframe src=\"https:\/\/www.google.com\/maps\/embed?pb=!1m18!1m12!1m3!1d7787.33417310762!2d-16.922787411571903!3d32.64222605486035!2m3!1f0!2f0!3f0!3m2!1i1024!2i768!4f13.1!3m3!1m2!1s0xc605ffbaf9a3e8d%3A0xbbad757d1549c835!2sRoyal%20Savoy%20Madeira!5e0!3m2!1ses!2spt!4v1722966035941!5m2!1ses!2spt\" width=\"600\" height=\"450\" style=\"border:0;\" allowfullscreen=\"\" loading=\"lazy\" referrerpolicy=\"no-referrer-when-downgrade\"><\/iframe>",
        "store_image": "shopify:\/\/shop_images\/image_169.png",
        "logo": "shopify:\/\/shop_images\/Logos_MS-01.svg"
      }
    }
  },
  "order": [
    "image_banner_jVfcNT",
    "svg_text_column_8a7bL6",
    "shape_carousel_collections_KVVNwB",
    "product_carousel_rmipzA",
    "wide_banner_rKTG8i",
    "collections_navigation_preview_J9bqUd",
    "collection_carousel_rnKXtp",
    "map_store_location_jem9Qa"
  ]
}
